<?xml version="1.0" encoding="utf-8"?>
<!DOCTYPE hibernate-mapping PUBLIC "-//Hibernate/Hibernate Mapping DTD 3.0//EN"
"http://hibernate.sourceforge.net/hibernate-mapping-3.0.dtd">
<!-- 
    Mapping file autogenerated by MyEclipse - Hibernate Tools
-->
<hibernate-mapping>
    <class name="com.marta.admin.hibernate.UpassAddress" table="UPASS_ADDRESS">
        <id name="upassaddressid" type="java.lang.Long">
            <column name="UPASSADDRESSID" precision="22" scale="0" />
             <generator class="sequence" >
    	        <param name="sequence">UPASSADDRESSID</param>      
            </generator> 
        </id>
        <many-to-one name="upassSchools" class="com.marta.admin.hibernate.UpassSchools" fetch="select" >
            <column name="SCHOOLID" precision="22" scale="0" not-null="true" />
        </many-to-one>
        <many-to-one name="bcwtstate" class="com.marta.admin.hibernate.BcwtState" fetch="select" >
            <column name="STATEID" precision="22" scale="0" not-null="true" />
        </many-to-one>
        <property name="nickname" type="java.lang.String">
            <column name="NICKNAME" />
        </property>
        <property name="addresseename" type="java.lang.String">
            <column name="ADDRESSEENAME" />
        </property>
        <property name="address1" type="java.lang.String">
            <column name="ADDRESS1" />
        </property>
        <property name="address2" type="java.lang.String">
            <column name="ADDRESS2" />
        </property>
        <property name="city" type="java.lang.String">
            <column name="CITY" />
        </property>
        <property name="zip" type="java.lang.String">
            <column name="ZIP" />
        </property>
        <property name="activestatus" type="java.lang.String">
            <column name="ACTIVESTATUS" length="3" />
        </property>
        <property name="istemporary" type="java.lang.String">
            <column name="ISTEMPORARY" length="3" />
        </property>
       
    </class>
</hibernate-mapping>
